README.rst
setup.py
django_mobile_template.egg-info/PKG-INFO
django_mobile_template.egg-info/SOURCES.txt
django_mobile_template.egg-info/dependency_links.txt
django_mobile_template.egg-info/top_level.txt
mobile_template/__init__.py
mobile_template/admin.py
mobile_template/apps.py
mobile_template/models.py
mobile_template/tests.py
mobile_template/views.py