Metadata-Version: 1.1
Name: django-mobile-template
Version: 0.1
Summary: Simple app that dynamically changes the templates based on domain/subdomain.
Home-page: https://github.com/linevich/django-mobile-template
Author: Anton Linevych
Author-email: mail@linevich.net
License: Apache 2.0
Platform: UNKNOWN
Classifier: Environment :: Web Environment
Classifier: Framework :: Django
Classifier: Intended Audience :: Developers
Classifier: License :: OSI Approved :: MIT License
Classifier: Operating System :: OS Independent
Classifier: Programming Language :: Python
Classifier: Programming Language :: Python :: 3
Classifier: Programming Language :: Python :: 3.4
Classifier: Programming Language :: Python :: 3.5
Classifier: Topic :: Internet :: WWW/HTTP
Classifier: Topic :: Internet :: WWW/HTTP :: Dynamic Content
